pymathalgos/__init__.py
pymathalgos-0.2.2.dist-info/WHEEL
pymathalgos-0.2.2.dist-info/METADATA
pymathalgos-0.2.2.dist-info/RECORD
