Metadata-Version: 2.1
Name: pymathalgos
Version: 0.2.2
Summary: 
Author: Adi58816
Author-email: adisalimgereev@gmail.com
Requires-Python: >=3.8,<4.0
Classifier: Programming Language :: Python :: 3
Classifier: Programming Language :: Python :: 3.8
